triplerecovery/__init__.py
triplerecovery/authenticate.py
triplerecovery/embed.py
triplerecovery/recover.py
triplerecovery/bits/__init__.py
triplerecovery/bits/authentication/__init__.py
triplerecovery/bits/authentication/embed.py
triplerecovery/bits/authentication/extract.py
triplerecovery/bits/authentication/make.py
triplerecovery/bits/recovery/__init__.py
triplerecovery/bits/recovery/embed.py
triplerecovery/bits/recovery/extract.py
triplerecovery/bits/recovery/make.py
triplerecovery/blocks/__init__.py
triplerecovery/blocks/combine.py
triplerecovery/blocks/make.py
triplerecovery/constants/__init__.py
triplerecovery/constants/lookups.py
triplerecovery/utils/__init__.py
triplerecovery/utils/utils.py
triplerecovery-0.0.8.dist-info/LICENSE
triplerecovery-0.0.8.dist-info/METADATA
triplerecovery-0.0.8.dist-info/WHEEL
triplerecovery-0.0.8.dist-info/top_level.txt
triplerecovery-0.0.8.dist-info/RECORD
