Metadata-Version: 2.1
Name: triplerecovery
Version: 0.0.8
Summary: Triple Recovery paper implementation in python
Home-page: https://github.com/crackaf/triple-recovery
Author: Hunzlah Malik
Author-email: hunzlahmalik@gmail.com
Classifier: Programming Language :: Python :: 3
Classifier: License :: OSI Approved :: MIT License
Classifier: Operating System :: OS Independent
License-File: LICENSE
Requires-Dist: numpy (>=1.22.4)
Requires-Dist: opencv-python (>=4.6.0.66)
Provides-Extra: test
Requires-Dist: pytest (>=7.1.2) ; extra == 'test'
